{
  "components": [
    {
      "tag": "ae-hello",
      "dependencies": [],
      "componentClass": "AeHello",
      "componentPath": "hello/ae-hello.js",
      "styles": {},
      "props": [
        {
          "name": "first",
          "type": "String"
        },
        {
          "name": "last",
          "type": "String"
        }
      ],
      "states": [
        {
          "name": "isVisible"
        }
      ]
    }
  ],
  "compiler": {
    "name": "@stencil/core",
    "version": "0.6.5",
    "typescriptVersion": "2.7.2"
  }
}